skillcornerviz/__init__.py
skillcornerviz/resources/__init__.py
skillcornerviz/resources/Roboto/Roboto-Black.ttf
skillcornerviz/resources/Roboto/Roboto-BlackItalic.ttf
skillcornerviz/resources/Roboto/Roboto-Bold.ttf
skillcornerviz/resources/Roboto/Roboto-BoldItalic.ttf
skillcornerviz/resources/Roboto/Roboto-Italic.ttf
skillcornerviz/resources/Roboto/Roboto-Light.ttf
skillcornerviz/resources/Roboto/Roboto-LightItalic.ttf
skillcornerviz/resources/Roboto/Roboto-Medium.ttf
skillcornerviz/resources/Roboto/Roboto-MediumItalic.ttf
skillcornerviz/resources/Roboto/Roboto-Regular.ttf
skillcornerviz/resources/Roboto/Roboto-Thin.ttf
skillcornerviz/resources/Roboto/Roboto-ThinItalic.ttf
skillcornerviz/standard_plots/__init__.py
skillcornerviz/standard_plots/bar_plot.py
skillcornerviz/standard_plots/formating.py
skillcornerviz/standard_plots/radar_plot.py
skillcornerviz/standard_plots/scatter_plot.py
skillcornerviz/standard_plots/summary_table.py
skillcornerviz/standard_plots/swarm_violin_plot.py
skillcornerviz/utils/__init__.py
skillcornerviz/utils/constants.py
skillcornerviz/utils/skillcorner_colors.py
skillcornerviz/utils/skillcorner_game_intelligence_utils.py
skillcornerviz/utils/skillcorner_physical_utils.py
skillcornerviz/utils/skillcorner_utils.py
skillcornerviz-1.1.2.dist-info/LICENSE
skillcornerviz-1.1.2.dist-info/METADATA
skillcornerviz-1.1.2.dist-info/WHEEL
skillcornerviz-1.1.2.dist-info/top_level.txt
skillcornerviz-1.1.2.dist-info/RECORD
