Metadata-Version: 2.1
Name: skillcornerviz
Version: 1.1.2
Summary: A Python package for processing and visualizing data SkillCorner data. This enables a user to produce visualizations with the SkillCorner brand style with a minimum of changes
Home-page: https://github.com/liamMichaelBailey/skillcornerviz
Author: Liam Bailey, Markos Bontozoglou, Micheal Nanopoulos, SkillCorner
Author-email: liam.bailey@skillcorner.com
Project-URL: GitHub, https://github.com/liamMichaelBailey/skillcornerviz
Classifier: Development Status :: 4 - Beta
Classifier: Intended Audience :: Other Audience
Classifier: License :: OSI Approved :: MIT License
Classifier: Programming Language :: Python :: 3
Classifier: Programming Language :: Python :: 3.7
Classifier: Programming Language :: Python :: 3.8
Classifier: Programming Language :: Python :: 3.9
Classifier: Operating System :: OS Independent
Requires-Python: >=3.8
License-File: LICENSE
Requires-Dist: adjustText >=0.7.3
Requires-Dist: matplotlib >=3.7.2
Requires-Dist: numpy >=1.24.2
Requires-Dist: pandas >=1.5.3
Requires-Dist: seaborn >=0.11.2
Requires-Dist: setuptools >=65.0.0
